bloramc/__init__.py
bloramc-0.0.1.dist-info/METADATA
bloramc-0.0.1.dist-info/WHEEL
bloramc-0.0.1.dist-info/top_level.txt
bloramc-0.0.1.dist-info/RECORD
